LICENSE
README.md
setup.py
school/__init__.py
school/school.py
univ.egg-info/PKG-INFO
univ.egg-info/SOURCES.txt
univ.egg-info/dependency_links.txt
univ.egg-info/top_level.txt