Metadata-Version: 2.1
Name: univ
Version: 0.0.1
Summary: Pypi school package management
Home-page: https://github.com/Jyonn/School
Author: Jyonn Liu
Author-email: i@6-79.cn
License: MIT Licence
Keywords: school,university
Platform: any
License-File: LICENSE
